sendbee_api/__init__.py
sendbee_api/auth.py
sendbee_api/bind.py
sendbee_api/client.py
sendbee_api/constants.py
sendbee_api/debug.py
sendbee_api/exceptions.py
sendbee_api/fields.py
sendbee_api/formatter.py
sendbee_api/models.py
sendbee_api/query_params.py
sendbee_api/response.py
sendbee_api/automation/__init__.py
sendbee_api/automation/client.py
sendbee_api/automation/models.py
sendbee_api/automation/query_params.py
sendbee_api/contacts/__init__.py
sendbee_api/contacts/client.py
sendbee_api/contacts/models.py
sendbee_api/contacts/query_params.py
sendbee_api/conversations/__init__.py
sendbee_api/conversations/client.py
sendbee_api/conversations/models.py
sendbee_api/conversations/query_params.py
sendbee_api/rate_limit/__init__.py
sendbee_api/rate_limit/client.py
sendbee_api/rate_limit/models.py
sendbee_api/rate_limit/query_params.py
sendbee_api/teams/__init__.py
sendbee_api/teams/client.py
sendbee_api/teams/models.py
sendbee_api/teams/query_params.py
sendbee_api-1.7.0.dist-info/LICENSE
sendbee_api-1.7.0.dist-info/METADATA
sendbee_api-1.7.0.dist-info/WHEEL
sendbee_api-1.7.0.dist-info/top_level.txt
sendbee_api-1.7.0.dist-info/RECORD
