Metadata-Version: 2.1
Name: sendbee-api
Version: 1.7.0
Summary: Python client SDK for Sendbee Public API
Home-page: https://github.com/sendbee/sendbee-python-client
Author: Sendbee ltd
Author-email: info@sendbee.io
License: MIT
Project-URL: Source, https://github.com/sendbee/sendbee-python-client
Keywords: sendbee api python
Platform: UNKNOWN
Classifier: Intended Audience :: Developers
Classifier: Topic :: Software Development :: Build Tools
Classifier: License :: OSI Approved :: MIT License
Classifier: Programming Language :: Python :: 3.6
Classifier: Programming Language :: Python :: 3.7
Classifier: Programming Language :: Python :: 3.8
Classifier: Programming Language :: Python :: 3.9
License-File: LICENSE
Requires-Dist: click (>=7.0)
Requires-Dist: requests (>=2.20.0)
Requires-Dist: dumpit (>=0.5.0)
Requires-Dist: aenum (>=2.1.2)
Requires-Dist: ujson (==2.0.1)
Requires-Dist: cryptography (>=3.2)
